Metadata-Version: 2.1
Name: py-ztj-mysql
Version: 2.0.0
Summary: python mysql instance package
Home-page: https://github.com/ztj1993/py-mysql
Author: ZhangTianJie
Author-email: ztj1993@gmail.com
License: MIT License
Keywords: mysql
Platform: UNKNOWN
Requires-Dist: pymysql
Requires-Dist: DBUtils
